doc/source/conf.py
redvypr/VERSION
redvypr/__init__.py
redvypr/data_packets.py
redvypr/device.py
redvypr/files.py
redvypr/gui.py
redvypr/logging_utils.py
redvypr/packet_statistic.py
redvypr/redvypr.py
redvypr/redvypr_address.py
redvypr/redvypr_main.py
redvypr/redvypr_main_widget.py
redvypr/version.py
redvypr/devices/__init__.py
redvypr/devices/db/__init__.py
redvypr/devices/develop/__init__.py
redvypr/devices/develop/influxdb_device.py
redvypr/devices/develop/iored.py
redvypr/devices/develop/zeromq_device.py
redvypr/devices/fileio/__init__.py
redvypr/devices/fileio/fileread.py
redvypr/devices/fileio/csvwriter/__init__.py
redvypr/devices/fileio/csvwriter/csvwriter.py
redvypr/devices/fileio/netcdfwriter/__init__.py
redvypr/devices/fileio/netcdfwriter/netcdfwriter.py
redvypr/devices/fileio/rawdatawriter/__init__.py
redvypr/devices/fileio/rawdatawriter/rawdatareplay.py
redvypr/devices/fileio/rawdatawriter/rawdatawriter.py
redvypr/devices/fileio/sqlite3/__init__.py
redvypr/devices/fileio/sqlite3/sqlite3db.py
redvypr/devices/fileio/sqlite3/sqlite3replay.py
redvypr/devices/fileio/sqlite3/sqlite3writer.py
redvypr/devices/fileio/xlsxwriter/__init__.py
redvypr/devices/fileio/xlsxwriter/xlsxwriter.py
redvypr/devices/interface/__init__.py
redvypr/devices/interface/manual_input.py
redvypr/devices/interface/serial.py
redvypr/devices/interface/serial_single.py
redvypr/devices/network/__init__.py
redvypr/devices/network/network.py
redvypr/devices/plot/PcolorPlotDevice.py
redvypr/devices/plot/TablePlotDevice.py
redvypr/devices/plot/TablePlotWidget.py
redvypr/devices/plot/XYPlotDevice.py
redvypr/devices/plot/XYPlotWidget.py
redvypr/devices/plot/__init__.py
redvypr/devices/plot/plot.py
redvypr/devices/plot/rawdatadisp.py
redvypr/devices/processing/__init__.py
redvypr/devices/processing/datafilter.py
redvypr/devices/processing/nmeaparser.py
redvypr/devices/sensors/__init__.py
redvypr/devices/sensors/calibration/__init__.py
redvypr/devices/sensors/calibration/autocalibration.py
redvypr-0.9.14.dist-info/licenses/LICENSE
redvypr-0.9.14.dist-info/METADATA
redvypr-0.9.14.dist-info/WHEEL
redvypr-0.9.14.dist-info/entry_points.txt
redvypr-0.9.14.dist-info/top_level.txt
redvypr-0.9.14.dist-info/RECORD
