Metadata-Version: 2.4
Name: redvypr
Version: 0.9.14
Summary: redvypr: REaltime Data Viewer and PRocessor (in PYthon)
Author-email: Peter Holtermann <peter.holtermann@io-warnemuende.de>
License: GPLv03
Classifier: Development Status :: 4 - Beta
Classifier: Topic :: Scientific/Engineering
Classifier: Intended Audience :: Science/Research
Classifier: License :: OSI Approved :: GNU General Public License v3 (GPLv3)
Classifier: Operating System :: OS Independent
Classifier: Programming Language :: Python :: 3 :: Only
Requires-Python: >=3.7
License-File: LICENSE
Requires-Dist: pyaml
Requires-Dist: pyqtgraph
Requires-Dist: PyQt6
Requires-Dist: setuptools
Requires-Dist: netCDF4
Requires-Dist: pyqtconsole
Requires-Dist: pyserial
Requires-Dist: qtawesome
Requires-Dist: pynmea2
Requires-Dist: pydantic>2.0
Requires-Dist: xlsxwriter
Requires-Dist: pympler
Requires-Dist: matplotlib
Requires-Dist: python-dateutil
Requires-Dist: pympler
Requires-Dist: autodoc_pydantic
Requires-Dist: deepdiff
Requires-Dist: xarray
Requires-Dist: reportlab
Requires-Dist: pytz
Requires-Dist: pytest
Dynamic: license-file
